fastbase/__init__.py
fastbase/exceptions.py
fastbase/fastauth.iml
fastbase/globals.py
fastbase/main.py
fastbase/models/Group.py
fastbase/models/Role.py
fastbase/models/UserMod.py
fastbase/models/__init__.py
fastbase/models/interface.py
fastbase/models/mixins.py
fastbase/models/optional.py
fastbase/schemas.py
fastbase/utils.py
fastbase-0.4.0.dist-info/METADATA
fastbase-0.4.0.dist-info/WHEEL
fastbase-0.4.0.dist-info/RECORD
