Metadata-Version: 2.1
Name: fastbase
Version: 0.4.0
Summary: 
Home-page: https://github.com/enchance/fastbase.git
License: MIT
Keywords: firebase,fastapi,sqlmodel,authentication,api,rest
Author: enchance
Author-email: enchance@gmail.com
Requires-Python: >=3.11,<4.0
Classifier: Intended Audience :: Developers
Classifier: Intended Audience :: Science/Research
Classifier: Intended Audience :: System Administrators
Classifier: License :: OSI Approved :: MIT License
Classifier: Operating System :: OS Independent
Classifier: Programming Language :: Python :: 3
Classifier: Programming Language :: Python :: 3.11
Classifier: Programming Language :: Python :: 3.12
Classifier: Topic :: Database
Classifier: Topic :: Database :: Database Engines/Servers
Classifier: Topic :: Internet
Classifier: Topic :: Internet :: WWW/HTTP
Classifier: Topic :: Internet :: WWW/HTTP :: HTTP Servers
Classifier: Typing :: Typed
Requires-Dist: arrow (>=1.3.0,<2.0.0)
Requires-Dist: fastapi (>=0.104.1,<0.105.0)
Requires-Dist: firebase-admin (>=6.3.0,<7.0.0)
Requires-Dist: icecream (>=2.1.3,<3.0.0)
Requires-Dist: pydantic (>=1.9.0,<2.0.0)
Requires-Dist: redis-om (>=0.2.1,<0.3.0)
Requires-Dist: sqlmodel (>=0.0.12,<0.0.13)
Project-URL: Repository, https://github.com/enchance/fastbase.git
